Metadata-Version: 2.1
Name: pyjsonq
Version: 1.0.2
Summary: Query over Json file
Home-page: https://github.com/s1s1ty/py-jsonq/
Author: Shaonty Dutta
Author-email: shaonty.dutta@gmail.com
License: MIT
Keywords: Python,plugin
Platform: UNKNOWN
Classifier: Development Status :: 4 - Beta
Classifier: Intended Audience :: Developers
Classifier: Natural Language :: English
Classifier: Operating System :: OS Independent
Classifier: Topic :: Software Development :: Libraries :: Python Modules
Classifier: Programming Language :: Python :: 2
Classifier: Programming Language :: Python :: 3
